{
  "test_results": [
    {
      "name": "TestAPI.test_validate_invalid_phone",
      "status": "fail",
      "duration_ms": null,
      "details": "AssertionError: API returns 200 OK for an invalid phone number, expected 400 Bad Request."
    },
    {
      "name": "TestEmailValidator.test_valid_emails",
      "status": "fail",
      "duration_ms": null,
      "details": "AssertionError: Email validator incorrectly identifies 'user@123.123.123.123' as invalid."
    },
    {
      "name": "TestPhoneValidator.test_invalid_phones",
      "status": "fail",
      "duration_ms": null,
      "details": "AssertionError: Phone validator incorrectly identifies '123456789' as valid."
    },
    {
      "name": "Other tests (passed)",
      "status": "pass",
      "duration_ms": null,
      "details": "6 tests passed successfully (specific names not provided in output)."
    }
  ],
  "coverage_pct": null,
  "security_issues": [],
  "performance_notes": [],
  "recommendation": "fix_required",
  "blocking_issues": [
    "API returns incorrect status code (200 instead of 400) for invalid phone number validation requests.",
    "Email validation logic is flawed, failing to recognize valid email addresses with IP address domains.",
    "Phone validation logic is flawed, incorrectly validating clearly invalid phone numbers."
  ],
  "non_blocking_issues": [
    "DeprecationWarning: Usage of `datetime.datetime.utcnow()` is deprecated and should be updated to timezone-aware objects (e.g., `datetime.datetime.now(datetime.UTC)`). This affects multiple API endpoints.",
    "The 'build' step was skipped according to the build results. While not directly impacting this test run, it's an unusual status that might indicate an incomplete CI/CD setup or a missing build artifact generation step."
  ],
  "build_verification": {
    "grade": "C-",
    "verdict": "Tests failed \u2014 implementation has issues",
    "syntax": "6/6 files pass",
    "lint_issues": 0,
    "build": "skipped",
    "tests": "fail"
  },
  "project_id": "PROJ-20260309-063405"
}